t_level/__init__.py
t_level/ecmprobs.db
t_level/rho.py
t_level-1.0.0.dist-info/METADATA
t_level-1.0.0.dist-info/WHEEL
t_level-1.0.0.dist-info/entry_points.txt
t_level-1.0.0.dist-info/top_level.txt
t_level-1.0.0.dist-info/RECORD
