Metadata-Version: 2.4
Name: t-level
Version: 1.0.0
Summary: Command line utility for calculating the t-level achieved by running a given number of ECM curves.
Requires-Python: >=3.9
Requires-Dist: gmpy2
